base62.py
pybase62-0.6.0.dist-info/LICENSE
pybase62-0.6.0.dist-info/METADATA
pybase62-0.6.0.dist-info/WHEEL
pybase62-0.6.0.dist-info/top_level.txt
pybase62-0.6.0.dist-info/RECORD
