Metadata-Version: 2.1
Name: pybase62
Version: 0.6.0
Summary: Python module for base62 encoding
Home-page: http://github.com/suminb/base62
Author: Sumin Byeon
Author-email: suminb@gmail.com
Classifier: Programming Language :: Python :: 3.6
Classifier: Programming Language :: Python :: 3.7
Classifier: Programming Language :: Python :: 3.8
Classifier: Programming Language :: Python :: 3.9
Classifier: Programming Language :: Python :: 3.10
Classifier: Programming Language :: Python :: 3.11
License-File: LICENSE
